nibabel/.gitignore
nibabel/__init__.py
nibabel/_version.py
nibabel/affines.py
nibabel/analyze.py
nibabel/arrayproxy.py
nibabel/arraywriters.py
nibabel/batteryrunners.py
nibabel/brikhead.py
nibabel/caret.py
nibabel/casting.py
nibabel/conftest.py
nibabel/data.py
nibabel/dataobj_images.py
nibabel/deprecated.py
nibabel/deprecator.py
nibabel/dft.py
nibabel/ecat.py
nibabel/environment.py
nibabel/eulerangles.py
nibabel/filebasedimages.py
nibabel/fileholders.py
nibabel/filename_parser.py
nibabel/fileslice.py
nibabel/fileutils.py
nibabel/funcs.py
nibabel/imageclasses.py
nibabel/imageglobals.py
nibabel/imagestats.py
nibabel/info.py
nibabel/loadsave.py
nibabel/minc1.py
nibabel/minc2.py
nibabel/mriutils.py
nibabel/nifti1.py
nibabel/nifti2.py
nibabel/onetime.py
nibabel/openers.py
nibabel/optpkg.py
nibabel/orientations.py
nibabel/parrec.py
nibabel/pkg_info.py
nibabel/processing.py
nibabel/py.typed
nibabel/pydicom_compat.py
nibabel/quaternions.py
nibabel/rstutils.py
nibabel/spaces.py
nibabel/spatialimages.py
nibabel/spm2analyze.py
nibabel/spm99analyze.py
nibabel/tmpdirs.py
nibabel/tripwire.py
nibabel/viewers.py
nibabel/volumeutils.py
nibabel/wrapstruct.py
nibabel/xmlutils.py
nibabel/benchmarks/__init__.py
nibabel/benchmarks/bench_array_to_file.py
nibabel/benchmarks/bench_arrayproxy_slicing.py
nibabel/benchmarks/bench_fileslice.py
nibabel/benchmarks/bench_finite_range.py
nibabel/benchmarks/bench_load_save.py
nibabel/benchmarks/butils.py
nibabel/benchmarks/pytest.benchmark.ini
nibabel/cifti2/__init__.py
nibabel/cifti2/cifti2.py
nibabel/cifti2/cifti2_axes.py
nibabel/cifti2/parse_cifti2.py
nibabel/cifti2/tests/__init__.py
nibabel/cifti2/tests/test_axes.py
nibabel/cifti2/tests/test_cifti2.py
nibabel/cifti2/tests/test_cifti2io_axes.py
nibabel/cifti2/tests/test_cifti2io_header.py
nibabel/cifti2/tests/test_name.py
nibabel/cifti2/tests/test_new_cifti2.py
nibabel/cmdline/__init__.py
nibabel/cmdline/conform.py
nibabel/cmdline/convert.py
nibabel/cmdline/dicomfs.py
nibabel/cmdline/diff.py
nibabel-5.0.1.dist-info/METADATA
nibabel-5.0.1.dist-info/WHEEL
nibabel-5.0.1.dist-info/entry_points.txt
nibabel-5.0.1.dist-info/licenses/COPYING
nibabel-5.0.1.dist-info/RECORD
