Metadata-Version: 2.1
Name: nibabel
Version: 5.0.1
Summary: Access a multitude of neuroimaging data formats
Project-URL: Homepage, https://nipy.org/nibabel
Project-URL: Development, https://github.com/nipy/nibabel
Author-email: NiBabel developers <neuroimaging@python.org>
Maintainer: Christopher Markiewicz
License: MIT License
License-File: COPYING
Classifier: Development Status :: 5 - Production/Stable
Classifier: Environment :: Console
Classifier: Intended Audience :: Science/Research
Classifier: License :: OSI Approved :: MIT License
Classifier: Operating System :: OS Independent
Classifier: Programming Language :: Python
Classifier: Programming Language :: Python :: 3.8
Classifier: Programming Language :: Python :: 3.9
Classifier: Programming Language :: Python :: 3.10
Classifier: Programming Language :: Python :: 3.11
Classifier: Topic :: Scientific/Engineering
Requires-Python: >=3.8
Requires-Dist: numpy>=1.19
Requires-Dist: packaging>=17
Requires-Dist: setuptools
Provides-Extra: all
Requires-Dist: nibabel[dev,dicomfs,doc,minc2,spm,style,test,zstd]; extra == 'all'
Provides-Extra: dev
Requires-Dist: gitpython; extra == 'dev'
Requires-Dist: nibabel[style]; extra == 'dev'
Requires-Dist: twine; extra == 'dev'
Provides-Extra: dicom
Requires-Dist: pydicom>=1.0.0; extra == 'dicom'
Provides-Extra: dicomfs
Requires-Dist: nibabel[dicom]; extra == 'dicomfs'
Requires-Dist: pillow; extra == 'dicomfs'
Provides-Extra: doc
Requires-Dist: matplotlib>=1.5.3; extra == 'doc'
Requires-Dist: numpydoc; extra == 'doc'
Requires-Dist: sphinx~=5.3; extra == 'doc'
Requires-Dist: texext; extra == 'doc'
Requires-Dist: tomli; python_version < '3.11' and extra == 'doc'
Provides-Extra: doctest
Requires-Dist: nibabel[doc,test]; extra == 'doctest'
Provides-Extra: minc2
Requires-Dist: h5py; extra == 'minc2'
Provides-Extra: spm
Requires-Dist: scipy; extra == 'spm'
Provides-Extra: style
Requires-Dist: blue; extra == 'style'
Requires-Dist: flake8; extra == 'style'
Requires-Dist: isort; extra == 'style'
Provides-Extra: test
Requires-Dist: coverage; extra == 'test'
Requires-Dist: pytest!=5.3.4; extra == 'test'
Requires-Dist: pytest-cov; extra == 'test'
Requires-Dist: pytest-doctestplus; extra == 'test'
Requires-Dist: pytest-httpserver; extra == 'test'
Requires-Dist: pytest-xdist; extra == 'test'
Provides-Extra: typing
Requires-Dist: mypy; extra == 'typing'
Requires-Dist: pydicom; extra == 'typing'
Requires-Dist: pytest; extra == 'typing'
Requires-Dist: types-pillow; extra == 'typing'
Requires-Dist: types-setuptools; extra == 'typing'
Provides-Extra: zstd
Requires-Dist: pyzstd>=0.14.3; extra == 'zstd'
